UART/uart_rx.v
module uart_rx (
    input clk,
    input rst,
    input rx,    //incoming data
    output reg [7:0] data
);
reg [1:0]states;
reg [3:0] bit_count;
reg [15:0] ticks;
reg [9:0] shift_reg;
reg flag;

parameter clk_freq=10000000;
parameter baud_rate=1000000;
localparam baud=clk_freq/baud_rate;

localparam idle=2'b00;
localparam start=2'b01;
localparam data_rx=2'b10;
localparam stop=2'b11;

always @ (posedge clk or posedge rst) begin
    if(rst) begin
        states<=idle;
        bit_count<=0;
        ticks<=0;
        shift_reg<=10'b0000000000;
        data<=8'b00000000;
    end
    else begin
        case(states)
            idle: begin
                bit_count<=0;
                ticks<=0;
                shift_reg<=10'b0000000000;
                if(rx==0) begin
                    states<=start;
                end   
            end
            start:begin
                if(ticks==baud/2 -1) begin
                    ticks<=0;
                    if(rx==0) begin
                        states<=data_rx;
                        shift_reg[bit_count]<=rx;
                        bit_count<=bit_count+1;
                    end
                    else begin
                        states<=idle;
                    end
                end
                else begin
                    ticks<=ticks+1;
                end
            end
            data_rx: begin
                if(ticks==baud-1) begin
                    ticks<=0;
                    if(bit_count==8) begin
                        states<=stop;
                    end
                    else begin
                        states<=data_rx;
                    end
                    shift_reg[bit_count]<=rx;
                    bit_count<=bit_count+1;
                end
                else begin
                    ticks<=ticks+1;
                end
            end
            stop:begin
                if(ticks==baud-1) begin
                    if(rx==1) begin
                        ticks<=0;
                        shift_reg[bit_count]<=rx;
                        states<=idle;
                        bit_count<=1'b0;
                        data<=shift_reg[8:1];
                    end
                    else begin
                        states <= idle;
                    end
                end
                else begin
                    ticks<=ticks+1;
                end
            end
        endcase
    end
end
endmodule

UART/uart_tx.v
module uart_tx (
    input clk, 
    input rst,
    input load,
    input [7:0] data,
    output reg tx,
    output reg busy
);
reg [1:0] states;
reg [3:0] bit_count;
parameter clk_freq=10000000;
parameter baud_rate=1000000;
localparam baud=clk_freq/baud_rate;
reg [15:0] tick=0;
reg [9:0] shift_reg;

localparam idle=2'b00;
localparam start=2'b01;
localparam data_tx=2'b10;
localparam stop=2'b11;

always @ (posedge clk or posedge rst) begin
    if(rst) begin
        states<=idle;
        bit_count<=0;
        tick<=0;
        tx<=1'b1;
        busy<=1'b0;
    end
    else begin
        case(states)
            idle: begin
                bit_count<=0;
                tick<=0;
                tx<=1'b1;
                busy<=1'b0;
                if(load) begin
                    states<=start;
                    busy<=1'b1;
                    shift_reg<={1'b1,data,1'b0};
                end
            end
            start: begin
                busy<=1'b1;
                if(tick==baud-1) begin
                    tick<=0;
                    tx<=shift_reg[0];
                    states<=data_tx;
                    bit_count<=bit_count+1;
                    shift_reg<=shift_reg>>1;
                end
                else begin
                    tick<=tick+1;
                end
            end
            data_tx: begin
                if(tick==baud-1) begin
                    tick<=0;
                    tx<=shift_reg[0];
                    if(bit_count==8) begin
                        states<=stop;
                        busy<=1'b0;
                    end
                    else begin
                        states<=data_tx;
                        busy<=1'b1;
                    end
                    bit_count<=bit_count+1;
                    shift_reg<=shift_reg >> 1;
                end
                else begin
                    tick<=tick+1;
                end
            end
            stop: begin
                busy<=1'b0;
                if(tick==baud-1) begin
                    tick<=0;
                    tx<=shift_reg[0];
                    states<=idle;
                    bit_count<=1'b0;
                end
                else begin
                    tick<=tick+1;
                end
            end
        endcase
    end
end
endmodule

UART/uart_loopback.v
module uart_loopback(

    input clk,
    input rst,
    input load,
    input [7:0] tx_data,
    output tx,
    output [7:0] rx_data,
    output busy

);

wire serial_line;

// UART TX
uart_tx transmitter(
    .clk(clk),
    .rst(rst),
    .load(load),
    .data(tx_data),
    .tx(serial_line),
    .busy(busy)
);

// UART RX
uart_rx receiver(
    .clk(clk),
    .rst(rst),
    .rx(serial_line),
    .data(rx_data)
);

// Optional external observation
assign tx = serial_line;

endmodule

UART/uart_loopback_tb.v
`timescale 1ns / 1ps

module uart_loopback_tb;

reg clk;
reg rst;
reg load;
reg [7:0] tx_data;

wire tx;
wire [7:0] rx_data;
wire busy;

// Instantiate loopback module
uart_loopback uut(
    .clk(clk),
    .rst(rst),
    .load(load),
    .tx_data(tx_data),
    .tx(tx),
    .rx_data(rx_data),
    .busy(busy)
);

// Clock generation
initial begin
    clk = 0;
    forever #5 clk = ~clk;
end

// Dump waves
initial begin
    $dumpfile("wave.vcd");
    $dumpvars(0, uart_loopback_tb);
end

initial begin

    // Initial values
    rst = 1;
    load = 0;
    tx_data = 8'b00000000;

    #20;
    rst = 0;

    // =====================================
    // FIRST TRANSMISSION
    // =====================================

    #20;

    tx_data = 8'b10110010;
    load = 1;

    #10;
    load = 0;

    // Wait until TX actually starts
    wait(busy == 1);

    // Wait until TX completes
    wait(busy == 0);

    // Give RX some extra cycles
    #300;

    $display("Received Data 1 = %b", rx_data);

    // =====================================
    // SECOND TRANSMISSION
    // =====================================

    #100;

    tx_data = 8'b11001100;
    load = 1;

    #10;
    load = 0;

    wait(busy == 1);
    wait(busy == 0);

    #300;

    $display("Received Data 2 = %b", rx_data);

    #200;

    $finish;

end

// Monitor signals
initial begin
    $monitor(
    "t=%0t tx=%b busy=%b rx_data=%b tx_state=%b rx_state=%b",
    $time,
    tx,
    busy,
    rx_data,
    uut.transmitter.states,
    uut.receiver.states
    );
end

endmodule

UART/wave.vcd
$date
	Thu May 28 22:31:16 2026
$end
$version
	Icarus Verilog
$end
$timescale
	1ps
$end
$scope module uart_loopback_tb $end
$var wire 1 ! tx $end
$var wire 8 " rx_data [7:0] $end
$var wire 1 # busy $end
$var reg 1 $ clk $end
$var reg 1 % load $end
$var reg 1 & rst $end
$var reg 8 ' tx_data [7:0] $end
$scope module uut $end
$var wire 1 $ clk $end
$var wire 1 % load $end
$var wire 1 & rst $end
$var wire 1 ! tx $end
$var wire 8 ( tx_data [7:0] $end
$var wire 1 ) serial_line $end
$var wire 8 * rx_data [7:0] $end
$var wire 1 # busy $end
$scope module receiver $end
$var wire 1 $ clk $end
$var wire 1 & rst $end
$var wire 1 ) rx $end
$var parameter 32 + baud $end
$var parameter 32 , baud_rate $end
$var parameter 32 - clk_freq $end
$var parameter 2 . data_rx $end
$var parameter 2 / idle $end
$var parameter 2 0 start $end
$var parameter 2 1 stop $end
$var reg 4 2 bit_count [3:0] $end
$var reg 8 3 data [7:0] $end
$var reg 10 4 shift_reg [9:0] $end
$var reg 2 5 states [1:0] $end
$var reg 16 6 ticks [15:0] $end
$upscope $end
$scope module transmitter $end
$var wire 1 $ clk $end
$var wire 8 7 data [7:0] $end
$var wire 1 % load $end
$var wire 1 & rst $end
$var parameter 32 8 baud $end
$var parameter 32 9 baud_rate $end
$var parameter 32 : clk_freq $end
$var parameter 2 ; data_tx $end
$var parameter 2 < idle $end
$var parameter 2 = start $end
$var parameter 2 > stop $end
$var reg 4 ? bit_count [3:0] $end
$var reg 1 # busy $end
$var reg 10 @ shift_reg [9:0] $end
$var reg 2 A states [1:0] $end
$var reg 16 B tick [15:0] $end
$var reg 1 ) tx $end
$upscope $end
$upscope $end
$upscope $end
$enddefinitions $end
$comment Show the parameter values. $end
$dumpall
b11 >
b1 =
b0 <
b10 ;
b100110001001011010000000 :
b11110100001001000000 9
b1010 8
b11 1
b1 0
b0 /
b10 .
b100110001001011010000000 -
b11110100001001000000 ,
b1010 +
$end
#0
$dumpvars
b0 B
b0 A
bx @
b0 ?
b0 7
b0 6
b0 5
b0 4
b0 3
b0 2
b0 *
1)
b0 (
b0 '
1&
0%
0$
0#
b0 "
1!
$end
#5000
1$
#10000
0$
#15000
1$
#20000
0$
0&
#25000
1$
#30000
0$
#35000
1$
#40000
0$
1%
b10110010 '
b10110010 (
b10110010 7
#45000
b1101100100 @
1#
b1 A
1$
#50000
0$
0%
#55000
b1 B
1$
#60000
0$
#65000
b10 B
1$
#70000
0$
#75000
b11 B
1$
#80000
0$
#85000
b100 B
1$
#90000
0$
#95000
b101 B
1$
#100000
0$
#105000
b110 B
1$
#110000
0$
#115000
b111 B
1$
#120000
0$
#125000
b1000 B
1$
#130000
0$
#135000
b1001 B
1$
#140000
0$
#145000
b110110010 @
b1 ?
b10 A
0!
0)
b0 B
1$
#150000
0$
#155000
b1 B
b1 5
1$
#160000
0$
#165000
b1 6
b10 B
1$
#170000
0$
#175000
b11 B
b10 6
1$
#180000
0$
#185000
b11 6
b100 B
1$
#190000
0$
#195000
b101 B
b100 6
1$
#200000
0$
#205000
b1 2
b10 5
b0 6
b110 B
1$
#210000
0$
#215000
b111 B
b1 6
1$
#220000
0$
#225000
b10 6
b1000 B
1$
#230000
0$
#235000
b1001 B
b11 6
1$
#240000
0$
#245000
b100 6
b11011001 @
b10 ?
b0 B
1$
#250000
0$
#255000
b1 B
b101 6
1$
#260000
0$
#265000
b110 6
b10 B
1$
#270000
0$
#275000
b11 B
b111 6
1$
#280000
0$
#285000
b1000 6
b100 B
1$
#290000
0$
#295000
b101 B
b1001 6
1$
#300000
0$
#305000
b10 2
b0 6
b110 B
1$
#310000
0$
#315000
b111 B
b1 6
1$
#320000
0$
#325000
b10 6
b1000 B
1$
#330000
0$
#335000
b1001 B
b11 6
1$
#340000
0$
#345000
b100 6
b1101100 @
b11 ?
1!
1)
b0 B
1$
#350000
0$
#355000
b1 B
b101 6
1$
#360000
0$
#365000
b110 6
b10 B
1$
#370000
0$
#375000
b11 B
b111 6
1$
#380000
0$
#385000
b1000 6
b100 B
1$
#390000
0$
#395000
b101 B
b1001 6
1$
#400000
0$
#405000
b11 2
b100 4
b0 6
b110 B
1$
#410000
0$
#415000
b111 B
b1 6
1$
#420000
0$
#425000
b10 6
b1000 B
1$
#430000
0$
#435000
b1001 B
b11 6
1$
#440000
0$
#445000
b100 6
b110110 @
b100 ?
0!
0)
b0 B
1$
#450000
0$
#455000
b1 B
b101 6
1$
#460000
0$
#465000
b110 6
b10 B
1$
#470000
0$
#475000
b11 B
b111 6
1$
#480000
0$
#485000
b1000 6
b100 B
1$
#490000
0$
#495000
b101 B
b1001 6
1$
#500000
0$
#505000
b100 2
b0 6
b110 B
1$
#510000
0$
#515000
b111 B
b1 6
1$
#520000
0$
#525000
b10 6
b1000 B
1$
#530000
0$
#535000
b1001 B
b11 6
1$
#540000
0$
#545000
b100 6
b11011 @
b101 ?
b0 B
1$
#550000
0$
#555000
b1 B
b101 6
1$
#560000
0$
#565000
b110 6
b10 B
1$
#570000
0$
#575000
b11 B
b111 6
1$
#580000
0$
#585000
b1000 6
b100 B
1$
#590000
0$
#595000
b101 B
b1001 6
1$
#600000
0$
#605000
b101 2
b0 6
b110 B
1$
#610000
0$
#615000
b111 B
b1 6
1$
#620000
0$
#625000
b10 6
b1000 B
1$
#630000
0$
#635000
b1001 B
b11 6
1$
#640000
0$
#645000
b100 6
b1101 @
b110 ?
1!
1)
b0 B
1$
#650000
0$
#655000
b1 B
b101 6
1$
#660000
0$
#665000
b110 6
b10 B
1$
#670000
0$
#675000
b11 B
b111 6
1$
#680000
0$
#685000
b1000 6
b100 B
1$
#690000
0$
#695000
b101 B
b1001 6
1$
#700000
0$
#705000
b110 2
b100100 4
b0 6
b110 B
1$
#710000
0$
#715000
b111 B
b1 6
1$
#720000
0$
#725000
b10 6
b1000 B
1$
#730000
0$
#735000
b1001 B
b11 6
1$
#740000
0$
#745000
b100 6
b110 @
b111 ?
b0 B
1$
#750000
0$
#755000
b1 B
b101 6
1$
#760000
0$
#765000
b110 6
b10 B
1$
#770000
0$
#775000
b11 B
b111 6
1$
#780000
0$
#785000
b1000 6
b100 B
1$
#790000
0$
#795000
b101 B
b1001 6
1$
#800000
0$
#805000
b111 2
b1100100 4
b0 6
b110 B
1$
#810000
0$
#815000
b111 B
b1 6
1$
#820000
0$
#825000
b10 6
b1000 B
1$
#830000
0$
#835000
b1001 B
b11 6
1$
#840000
0$
#845000
b100 6
b11 @
b1000 ?
0!
0)
b0 B
1$
#850000
0$
#855000
b1 B
b101 6
1$
#860000
0$
#865000
b110 6
b10 B
1$
#870000
0$
#875000
b11 B
b111 6
1$
#880000
0$
#885000
b1000 6
b100 B
1$
#890000
0$
#895000
b101 B
b1001 6
1$
#900000
0$
#905000
b1000 2
b0 6
b110 B
1$
#910000
0$
#915000
b111 B
b1 6
1$
#920000
0$
#925000
b10 6
b1000 B
1$
#930000
0$
#935000
b1001 B
b11 6
1$
#940000
0$
#945000
b100 6
b1 @
b1001 ?
0#
b11 A
1!
1)
b0 B
1$
#950000
0$
#955000
b1 B
b101 6
1$
#960000
0$
#965000
b110 6
b10 B
1$
#970000
0$
#975000
b11 B
b111 6
1$
#980000
0$
#985000
b1000 6
b100 B
1$
#990000
0$
#995000
b101 B
b1001 6
1$
#1000000
0$
#1005000
b1001 2
b101100100 4
b11 5
b0 6
b110 B
1$
#1010000
0$
#1015000
b111 B
b1 6
1$
#1020000
0$
#1025000
b10 6
b1000 B
1$
#1030000
0$
#1035000
b1001 B
b11 6
1$
#1040000
0$
#1045000
b100 6
b0 ?
b0 A
b0 B
1$
#1050000
0$
#1055000
b101 6
1$
#1060000
0$
#1065000
b110 6
1$
#1070000
0$
#1075000
b111 6
1$
#1080000
0$
#1085000
b1000 6
1$
#1090000
0$
#1095000
b1001 6
1$
#1100000
0$
#1105000
b10110010 "
b10110010 *
b10110010 3
b0 2
b0 5
b1101100100 4
b0 6
1$
#1110000
0$
#1115000
b0 4
1$
